{
    "AGV": {
        "checkpoints": [
            {
                "steps": 2499978,
                "file_path": "results\\6x3x3_ins_3\\AGV\\AGV-2499978.onnx",
                "reward": -24.989743383307207,
                "creation_time": 1667963694.2927861,
                "auxillary_file_paths": [
                    "results\\6x3x3_ins_3\\AGV\\AGV-2499978.pt"
                ]
            },
            {
                "steps": 2999979,
                "file_path": "results\\6x3x3_ins_3\\AGV\\AGV-2999979.onnx",
                "reward": -25.02976869187265,
                "creation_time": 1667964101.042193,
                "auxillary_file_paths": [
                    "results\\6x3x3_ins_3\\AGV\\AGV-2999979.pt"
                ]
            },
            {
                "steps": 3499980,
                "file_path": "results\\6x3x3_ins_3\\AGV\\AGV-3499980.onnx",
                "reward": -25.020713513490385,
                "creation_time": 1667964502.5494642,
                "auxillary_file_paths": [
                    "results\\6x3x3_ins_3\\AGV\\AGV-3499980.pt"
                ]
            },
            {
                "steps": 3999987,
                "file_path": "results\\6x3x3_ins_3\\AGV\\AGV-3999987.onnx",
                "reward": -25.11507491310044,
                "creation_time": 1667964912.8816488,
                "auxillary_file_paths": [
                    "results\\6x3x3_ins_3\\AGV\\AGV-3999987.pt"
                ]
            },
            {
                "steps": 4200089,
                "file_path": "results\\6x3x3_ins_3\\AGV\\AGV-4200089.onnx",
                "reward": -25.005899794896443,
                "creation_time": 1667965068.2313907,
                "auxillary_file_paths": [
                    "results\\6x3x3_ins_3\\AGV\\AGV-4200089.pt"
                ]
            }
        ],
        "final_checkpoint": {
            "steps": 4200089,
            "file_path": "results\\6x3x3_ins_3\\AGV.onnx",
            "reward": -25.005899794896443,
            "creation_time": 1667965068.2313907,
            "auxillary_file_paths": [
                "results\\6x3x3_ins_3\\AGV\\AGV-4200089.pt"
            ]
        }
    },
    "metadata": {
        "stats_format_version": "0.3.0",
        "mlagents_version": "0.28.0",
        "torch_version": "1.7.1+cu110"
    }
}