{
    "AGV": {
        "checkpoints": [
            {
                "steps": 13499991,
                "file_path": "results/9x9x2_256x128/AGV/AGV-13499991.onnx",
                "reward": -42.88956814720517,
                "creation_time": 1667627578.6702065,
                "auxillary_file_paths": [
                    "results/9x9x2_256x128/AGV/AGV-13499991.pt"
                ]
            },
            {
                "steps": 13999939,
                "file_path": "results/9x9x2_256x128/AGV/AGV-13999939.onnx",
                "reward": -42.0661678314209,
                "creation_time": 1667628235.304044,
                "auxillary_file_paths": [
                    "results/9x9x2_256x128/AGV/AGV-13999939.pt"
                ]
            },
            {
                "steps": 14499968,
                "file_path": "results/9x9x2_256x128/AGV/AGV-14499968.onnx",
                "reward": -40.857552664620535,
                "creation_time": 1667628856.7031019,
                "auxillary_file_paths": [
                    "results/9x9x2_256x128/AGV/AGV-14499968.pt"
                ]
            },
            {
                "steps": 14999922,
                "file_path": "results/9x9x2_256x128/AGV/AGV-14999922.onnx",
                "reward": -41.747474670410156,
                "creation_time": 1667629431.9762132,
                "auxillary_file_paths": [
                    "results/9x9x2_256x128/AGV/AGV-14999922.pt"
                ]
            },
            {
                "steps": 15000126,
                "file_path": "results/9x9x2_256x128/AGV/AGV-15000126.onnx",
                "reward": -41.24803924560547,
                "creation_time": 1667629432.052909,
                "auxillary_file_paths": [
                    "results/9x9x2_256x128/AGV/AGV-15000126.pt"
                ]
            }
        ],
        "final_checkpoint": {
            "steps": 15000126,
            "file_path": "results/9x9x2_256x128/AGV.onnx",
            "reward": -41.24803924560547,
            "creation_time": 1667629432.052909,
            "auxillary_file_paths": [
                "results/9x9x2_256x128/AGV/AGV-15000126.pt"
            ]
        }
    },
    "metadata": {
        "stats_format_version": "0.3.0",
        "mlagents_version": "0.28.0",
        "torch_version": "1.7.1"
    }
}